ingenii_azure_data_platform/__init__.py
ingenii_azure_data_platform/config.py
ingenii_azure_data_platform/defaults.py
ingenii_azure_data_platform/helpers.py
ingenii_azure_data_platform-0.0.6.dist-info/LICENSE
ingenii_azure_data_platform-0.0.6.dist-info/METADATA
ingenii_azure_data_platform-0.0.6.dist-info/WHEEL
ingenii_azure_data_platform-0.0.6.dist-info/dependency_links.txt
ingenii_azure_data_platform-0.0.6.dist-info/top_level.txt
ingenii_azure_data_platform-0.0.6.dist-info/RECORD
