Metadata-Version: 2.1
Name: ingenii-azure-data-platform
Version: 0.0.6
Summary: Configuration parsing and general utilities for the Ingenii Azure Data Platform IaC implementation.
Home-page: https://github.com/ingenii-solutions/azure-data-platform-python-package
Author: Teodor Kostadinov
Author-email: teodor@ingenii.dev
License: UNKNOWN
Platform: UNKNOWN
Classifier: Programming Language :: Python :: 3
Classifier: License :: OSI Approved :: Mozilla Public License 2.0 (MPL 2.0)
Classifier: Operating System :: OS Independent
Requires-Dist: pulumi-azure-native (<2.0,>=1.19.0)
Requires-Dist: HiYaPyCo (<0.5,>=0.4.16)
Requires-Dist: yamale (<4.0,>=3.0)
